fpdb/__init__.py
fpdb/forked_pdb.py
fpdb-0.0.0.dev2.dist-info/licenses/LICENSE
fpdb-0.0.0.dev2.dist-info/METADATA
fpdb-0.0.0.dev2.dist-info/WHEEL
fpdb-0.0.0.dev2.dist-info/top_level.txt
fpdb-0.0.0.dev2.dist-info/RECORD
