Metadata-Version: 2.4
Name: fpdb
Version: 0.0.0.dev2
Summary: Python package for debugging multi-processed code using PDB.
Author-email: Lightning AI <contact@lightning.ai>
License:                                  Apache License
Project-URL: documentation, https://github.com/lightning-AI/litgpt/tutorials
Project-URL: homepage, https://github.com/Lightning-AI/forked-pdb
Classifier: Programming Language :: Python :: 3 :: Only
Classifier: Programming Language :: Python :: 3.8
Classifier: Programming Language :: Python :: 3.9
Classifier: Programming Language :: Python :: 3.10
Classifier: Programming Language :: Python :: 3.11
Classifier: Programming Language :: Python :: 3.12
Classifier: Programming Language :: Python :: 3.13
License-File: LICENSE
Provides-Extra: test
Requires-Dist: pytest>=8.1.1; extra == "test"
Requires-Dist: pytest-rerunfailures>=14; extra == "test"
Requires-Dist: pytest-timeout>=2.3.1; extra == "test"
Dynamic: license-file
